<?xml version="1.0" encoding="UTF-8" standalone="no"?><PAYMENTS><payment><physical_payer><bank_account>payer91</bank_account><name>payer91</name><surname>payer91</surname><patronymic>payer91</patronymic><passport_series>payer91</passport_series><passport_number>payer91</passport_number><phone>payer91</phone></physical_payer><physical_recipient><bank_account>recipient91</bank_account><name>recipient91</name><surname>recipient91</surname><patronymic>recipient91</patronymic><passport_series>recipient91</passport_series><passport_number>recipient91</passport_number><phone>recipient91</phone></physical_recipient><details><bank_BIC>details91</bank_BIC><bank_name>details91</bank_name><total>2500.50</total><date_of_payment>2014-09-29</date_of_payment><date_of_execution>2014-10-01</date_of_execution><payment_code>details91</payment_code></details></payment><payment><legal_payer><bank_account>payer92</bank_account><TIN>payer92</TIN><company_name>payer92</company_name><company_address>payer92</company_address></legal_payer><legal_recipient><bank_account>recipient92</bank_account><TIN>recipient92</TIN><company_name>recipient92</company_name><company_address>recipient92</company_address></legal_recipient><details><bank_BIC>details92</bank_BIC><bank_name>details92</bank_name><total>2500.50</total><date_of_payment>2014-09-29</date_of_payment><date_of_execution>2014-10-01</date_of_execution><payment_code>details92</payment_code></details></payment><payment><physical_payer><bank_account>payer93</bank_account><name>payer93</name><surname>payer93</surname><patronymic>payer93</patronymic><passport_series>payer93</passport_series><passport_number>payer93</passport_number><phone>payer93</phone></physical_payer><legal_recipient><bank_account>recipient93</bank_account><TIN>recipient93</TIN><company_name>recipient93</company_name><company_address>recipient93</company_address></legal_recipient><details><bank_BIC>details93</bank_BIC><bank_name>details93</bank_name><total>2500.50</total><date_of_payment>2014-09-29</date_of_payment><date_of_execution>2014-10-01</date_of_execution><payment_code>details93</payment_code></details></payment><payment><physical_payer><bank_account>payer94</bank_account><name>payer94</name><surname>payer94</surname><patronymic>payer94</patronymic><passport_series>payer94</passport_series><passport_number>payer94</passport_number><phone>payer94</phone></physical_payer><physical_recipient><bank_account>recipient94</bank_account><name>recipient94</name><surname>recipient94</surname><patronymic>recipient94</patronymic><passport_series>recipient94</passport_series><passport_number>recipient94</passport_number><phone>recipient94</phone></physical_recipient><details><bank_BIC>details94</bank_BIC><bank_name>details94</bank_name><total>2500.50</total><date_of_payment>2014-09-29</date_of_payment><date_of_execution>2014-10-01</date_of_execution><payment_code>details94</payment_code></details></payment><payment><legal_payer><bank_account>payer95</bank_account><TIN>payer95</TIN><company_name>payer95</company_name><company_address>payer95</company_address></legal_payer><legal_recipient><bank_account>recipient95</bank_account><TIN>recipient95</TIN><company_name>recipient95</company_name><company_address>recipient95</company_address></legal_recipient><details><bank_BIC>details95</bank_BIC><bank_name>details95</bank_name><total>2500.50</total><date_of_payment>2014-09-29</date_of_payment><date_of_execution>2014-10-01</date_of_execution><payment_code>details95</payment_code></details></payment><payment><physical_payer><bank_account>payer96</bank_account><name>payer96</name><surname>payer96</surname><patronymic>payer96</patronymic><passport_series>payer96</passport_series><passport_number>payer96</passport_number><phone>payer96</phone></physical_payer><legal_recipient><bank_account>recipient96</bank_account><TIN>recipient96</TIN><company_name>recipient96</company_name><company_address>recipient96</company_address></legal_recipient><details><bank_BIC>details96</bank_BIC><bank_name>details96</bank_name><total>2500.50</total><date_of_payment>2014-09-29</date_of_payment><date_of_execution>2014-10-01</date_of_execution><payment_code>details96</payment_code></details></payment><payment><physical_payer><bank_account>payer97</bank_account><name>payer97</name><surname>payer97</surname><patronymic>payer97</patronymic><passport_series>payer97</passport_series><passport_number>payer97</passport_number><phone>payer97</phone></physical_payer><physical_recipient><bank_account>recipient97</bank_account><name>recipient97</name><surname>recipient97</surname><patronymic>recipient97</patronymic><passport_series>recipient97</passport_series><passport_number>recipient97</passport_number><phone>recipient97</phone></physical_recipient><details><bank_BIC>details97</bank_BIC><bank_name>details97</bank_name><total>2500.50</total><date_of_payment>2014-09-29</date_of_payment><date_of_execution>2014-10-01</date_of_execution><payment_code>details97</payment_code></details></payment><payment><legal_payer><bank_account>payer98</bank_account><TIN>payer98</TIN><company_name>payer98</company_name><company_address>payer98</company_address></legal_payer><legal_recipient><bank_account>recipient98</bank_account><TIN>recipient98</TIN><company_name>recipient98</company_name><company_address>recipient98</company_address></legal_recipient><details><bank_BIC>details98</bank_BIC><bank_name>details98</bank_name><total>2500.50</total><date_of_payment>2014-09-29</date_of_payment><date_of_execution>2014-10-01</date_of_execution><payment_code>details98</payment_code></details></payment><payment><physical_payer><bank_account>payer99</bank_account><name>payer99</name><surname>payer99</surname><patronymic>payer99</patronymic><passport_series>payer99</passport_series><passport_number>payer99</passport_number><phone>payer99</phone></physical_payer><legal_recipient><bank_account>recipient99</bank_account><TIN>recipient99</TIN><company_name>recipient99</company_name><company_address>recipient99</company_address></legal_recipient><details><bank_BIC>details99</bank_BIC><bank_name>details99</bank_name><total>2500.50</total><date_of_payment>2014-09-29</date_of_payment><date_of_execution>2014-10-01</date_of_execution><payment_code>details99</payment_code></details></payment><payment><physical_payer><bank_account>payer100</bank_account><name>payer100</name><surname>payer100</surname><patronymic>payer100</patronymic><passport_series>payer100</passport_series><passport_number>payer100</passport_number><phone>payer100</phone></physical_payer><physical_recipient><bank_account>recipient100</bank_account><name>recipient100</name><surname>recipient100</surname><patronymic>recipient100</patronymic><passport_series>recipient100</passport_series><passport_number>recipient100</passport_number><phone>recipient100</phone></physical_recipient><details><bank_BIC>details100</bank_BIC><bank_name>details100</bank_name><total>2500.50</total><date_of_payment>2014-09-29</date_of_payment><date_of_execution>2014-10-01</date_of_execution><payment_code>details100</payment_code></details></payment></PAYMENTS>